{
  "cities": [
    {
      "cityName": "Abrantes",
      "country": "Portugal",
      "emoji": "🇵🇹",
      "date": "2023-08-04T03:31:04.118Z",
      "notes": "always going to remember this one\n",
      "position": {
        "lat": "39.607665698027745",
        "lng": "-8.195800781250002"
      },
      "id": 2
    },
    {
      "cityName": "Boltana",
      "country": "Spain",
      "emoji": "🇪🇸",
      "date": "2023-08-04T04:10:25.471Z",
      "notes": "",
      "position": {
        "lat": "42.35946515421653",
        "lng": "-0.10986328125000001"
      },
      "id": 3
    }
  ]
}